MANIFEST.in
README.md
setup.py
tendenci_videos.egg-info/PKG-INFO
tendenci_videos.egg-info/SOURCES.txt
tendenci_videos.egg-info/dependency_links.txt
tendenci_videos.egg-info/requires.txt
tendenci_videos.egg-info/top_level.txt
videos/__init__.py
videos/admin.py
videos/app_registry.py
videos/feeds.py
videos/forms.py
videos/managers.py
videos/models.py
videos/search_indexes.py
videos/settings.json
videos/signals.py
videos/urls.py
videos/views.py
videos/migrations/0001_initial.py
videos/migrations/0002_auto__chg_field_video_creator__chg_field_video_entity__chg_field_video.py
videos/migrations/0003_auto__chg_field_video_slug.py
videos/migrations/0004_auto__add_videotype__add_field_video_video_type.py
videos/migrations/__init__.py
videos/static/css/video.css
videos/templates/search/indexes/videos/video_text.txt
videos/templates/videos/base.html
videos/templates/videos/details.html
videos/templates/videos/list.html
videos/templates/videos/meta.html
videos/templates/videos/options.html
videos/templates/videos/search-result.html
videos/templatetags/__init__.py
videos/templatetags/video_filters.py
videos/templatetags/video_tags.py